src/tdstools/__about__.py
src/tdstools/__init__.py
tds_tools-0.0.1.dist-info/METADATA
tds_tools-0.0.1.dist-info/WHEEL
tds_tools-0.0.1.dist-info/licenses/LICENSE.txt
tds_tools-0.0.1.dist-info/RECORD
