Metadata-Version: 2.1
Name: TDS-Tools
Version: 0.0.1
Project-URL: Documentation, https://github.com/unknown/tdstools#readme
Project-URL: Issues, https://github.com/unknown/tdstools/issues
Project-URL: Source, https://github.com/unknown/tdstools
Author-email: "J. Steven Dodge" <jsdodge@sfu.ca>
License-Expression: MIT
License-File: LICENSE.txt
Classifier: Development Status :: 1 - Planning
Classifier: Programming Language :: Python
Classifier: Programming Language :: Python :: 3.7
Classifier: Programming Language :: Python :: 3.8
Classifier: Programming Language :: Python :: 3.9
Classifier: Programming Language :: Python :: 3.10
Classifier: Programming Language :: Python :: 3.11
Classifier: Programming Language :: Python :: Implementation :: CPython
Classifier: Programming Language :: Python :: Implementation :: PyPy
Requires-Python: >=3.7
